sl_ai_models/__init__.py
sl_ai_models/claude35sonnet.py
sl_ai_models/claude3opus.py
sl_ai_models/deepgram_nova2.py
sl_ai_models/exa_searcher.py
sl_ai_models/gpt35_internet_archive_8pc.py
sl_ai_models/gpt35_scrape_cleaning.py
sl_ai_models/gpt4o.py
sl_ai_models/gpt4omini.py
sl_ai_models/gpt4ovision.py
sl_ai_models/perplexity.py
sl_ai_models/basic_model_interfaces/__init__.py
sl_ai_models/basic_model_interfaces/ai_model.py
sl_ai_models/basic_model_interfaces/incurs_cost.py
sl_ai_models/basic_model_interfaces/named_model.py
sl_ai_models/basic_model_interfaces/outputs_text.py
sl_ai_models/basic_model_interfaces/priced_per_request.py
sl_ai_models/basic_model_interfaces/request_limited_model.py
sl_ai_models/basic_model_interfaces/retryable_model.py
sl_ai_models/basic_model_interfaces/time_limited_model.py
sl_ai_models/basic_model_interfaces/token_limited_model.py
sl_ai_models/basic_model_interfaces/tokens_are_calculatable.py
sl_ai_models/basic_model_interfaces/tokens_incur_cost.py
sl_ai_models/model_archetypes/__init__.py
sl_ai_models/model_archetypes/anthropic_text_model.py
sl_ai_models/model_archetypes/deepgram_model.py
sl_ai_models/model_archetypes/openai_text_model.py
sl_ai_models/model_archetypes/openai_vision_model.py
sl_ai_models/model_archetypes/perplexity_text_model.py
sl_ai_models/model_archetypes/traditional_online_llm.py
sl_ai_models/resource_managers/__init__.py
sl_ai_models/resource_managers/hard_limit_manager.py
sl_ai_models/resource_managers/monetary_cost_manager.py
sl_ai_models/resource_managers/refreshing_bucket_rate_limiter.py
sl_ai_models/utils/__init__.py
sl_ai_models/utils/ai_misc.py
sl_ai_models/utils/async_batching.py
sl_ai_models/utils/custom_logger.py
sl_ai_models/utils/file_manipulation.py
sl_ai_models/utils/jsonable.py
sl_ai_models/utils/openai_utils.py
sl_ai_models/utils/response_types.py
sl_ai_models-0.0.19.dist-info/METADATA
sl_ai_models-0.0.19.dist-info/WHEEL
sl_ai_models-0.0.19.dist-info/top_level.txt
sl_ai_models-0.0.19.dist-info/RECORD
